cicada_script/__init__.py
cicada_script/__main__.py
cicada_script/core.py
cicada_script/geometry.py
cicada_script-0.1.0.dist-info/METADATA
cicada_script-0.1.0.dist-info/WHEEL
cicada_script-0.1.0.dist-info/entry_points.txt
cicada_script-0.1.0.dist-info/licenses/LICENSE
cicada_script-0.1.0.dist-info/licenses/LICENSE_CHANGE_NOTICE.md
cicada_script-0.1.0.dist-info/RECORD
