Metadata-Version: 2.4
Name: cicada-script
Version: 0.1.0
Summary: Python API for parametric CAD design and geometry automation
Project-URL: Homepage, https://github.com/cicada-cad/cicada-script
Project-URL: Documentation, https://cicada-script.readthedocs.io
Project-URL: Repository, https://github.com/cicada-cad/cicada-script.git
Project-URL: Bug Tracker, https://github.com/cicada-cad/cicada-script/issues
Project-URL: Changelog, https://github.com/cicada-cad/cicada-script/blob/main/CHANGELOG.md
Author-email: Cicada CAD Project <contact@cicada-cad.org>
License: Business Source License 1.1
License-File: LICENSE
License-File: LICENSE_CHANGE_NOTICE.md
Keywords: 3D,CAD,automation,cicada,design,geometry,parametric,scripting
Classifier: Development Status :: 4 - Beta
Classifier: Intended Audience :: Developers
Classifier: Intended Audience :: Education
Classifier: Intended Audience :: Science/Research
Classifier: License :: Other/Proprietary License
Classifier: Operating System :: OS Independent
Classifier: Programming Language :: Python :: 3
Classifier: Programming Language :: Python :: 3.8
Classifier: Programming Language :: Python :: 3.9
Classifier: Programming Language :: Python :: 3.10
Classifier: Programming Language :: Python :: 3.11
Classifier: Programming Language :: Python :: 3.12
Classifier: Topic :: Multimedia :: Graphics :: 3D Modeling
Classifier: Topic :: Scientific/Engineering
Classifier: Topic :: Scientific/Engineering :: Visualization
Classifier: Topic :: Software Development :: Libraries :: Python Modules
Requires-Python: >=3.8
Provides-Extra: dev
Requires-Dist: black>=23.0; extra == 'dev'
Requires-Dist: isort>=5.0; extra == 'dev'
Requires-Dist: mypy>=1.0; extra == 'dev'
Requires-Dist: pre-commit>=3.0; extra == 'dev'
Requires-Dist: pytest-cov>=4.0; extra == 'dev'
Requires-Dist: pytest>=7.0; extra == 'dev'
Provides-Extra: docs
Requires-Dist: myst-parser>=0.18; extra == 'docs'
Requires-Dist: sphinx-rtd-theme>=1.0; extra == 'docs'
Requires-Dist: sphinx>=5.0; extra == 'docs'
